[{"name":"Empanaditas de Pollo","desc":"2 pieces. Chicken ropa vieja, charred tomatillo and black bean puree.","price":"$10.00","warning":[]},{"name":"Empanaditas de Carne","desc":"2 pieces. Empanadas with picadillo.","price":"$10.00","warning":[]},{"name":"Empanaditas de Espinaca y Manchego","desc":"2 pieces. Spinach and Manchego cheese quince marmalade.","price":"$9.00","warning":["lactose","spinach"]},{"name":"Pulpo","desc":"Grilled Spanish octopus, black bean puree, manzanilla -olive salsa verde, charred onion and baby potatoes.","price":"$18.00","warning":["onion"]},{"name":"Escabeche de Camaron","desc":"Pickled shrimp, roasted tomato, jalapeno, avocado, sherry hot sauce and old bay plantain chips.","price":"$17.00","warning":["shellfish/fish","tomato"]},{"name":"Aguacate con Cangrejo","desc":"Cuban guacamole,super lump crab meat and plantain chips.","price":"$20.00","warning":["shellfish/fish"]},{"name":"Camaron al Ajillo","desc":"Garlic shrimp, guindilla pepper and toasted bread.","price":"$17.00","warning":["shellfish/fish","garlic"]},{"name":"Alitas Cubanas(wings)","desc":"Cuban style wing(bone-in) with BBQ Sauce & Blue Cheese","price":"$14.00","warning":["lactose"]},{"name":"El Cubano (cuban Sandwich)","desc":"Slow roasted pork,ham,cantimpalo,swiss cheese,pickles,garlic mojo","price":"$12.00","warning":["lactose","lactose","pork","garlic"]},{"name":"Masitas","desc":"Fried pork chunks, scallion, mojo, cilantro","price":"$14.00","warning":["pork"]},{"name":"EMPANADITAS TRIO","price":"$15.00","warning":[]},{"name":"Croquetas de Hongos","desc":"Wild mushroom croquette, truffle","price":"$12.00","warning":[]},{"name":"Croquetas de Jamon","desc":"Ham croquette, truffle aioli","price":"$13.00","warning":[]},{"name":"Ensalada Cesar","desc":"Little gem lettuce, chickpeas, bacon, roasted garlic crouton, buttermilk Caesar, farmers cheese. Add chicken for an additional charge.","price":"$13.00","warning":["lactose","lactose","pork","garlic","lettuce"]},{"name":"AGUACATE Y TOMATE","desc":"Avocado, tomato salad, shaved onion, sherry-oregano vinaigrette","price":"$13.00","warning":["tomato","onion"]},{"name":"Churrasco Plato","desc":"Grilled skirt steak, Cuban yuca fries, watercress salad and chimichurri.","price":"$35.00","warning":[]},{"name":"Mar y Tierra Plato","desc":"Grilled hanger steak, garlic shrimp, cream spinach, roasted potato and chimichurri.","price":"$30.00","warning":["shellfish/fish","spinach","garlic"]},{"name":"Ropa Vieja Plato","desc":"Twice cooked slow braised skirt steak, tomato pepper sauce, white rice and black beans.","price":"$28.00","warning":["tomato"]},{"name":"Vaca Frita Plato","desc":"Twice cooked crispy skirt steak, tomato escabeche, avocado, white rice, black beans and garlic mojo.","price":"$29.00","warning":["tomato","garlic"]},{"name":"Pollo Criollo Plato","desc":"Amish organic free-range boneless half chicken, chorizo sweet plantain fried rice and garlic onion mojo.","price":"$25.00","warning":["garlic","onion"]},{"name":"Pollo a la Parrilla Plato","desc":"White rice and black beans.","price":"$25.00","warning":[]},{"name":"El Clasico Plato","desc":"Roasted pork shank, Moro rice, garlic orange mojo, yuca con mojo, sweet plantain and pickled red onions.","price":"$24.00","warning":["pork","garlic","onion"]},{"name":"Salmon Plato","desc":"Pan-seared tomatillo glazed salmon, Spanish white sweet potato and ginger puree, baby kale and green apple salad.","price":"$28.00","warning":["apple","kale"]},{"name":"Paella Valenciana Plato","desc":"Saffron rice, bay scallops, shrimp, mussels, clams, chorizo, chicken and garlic aioli.","price":"$30.00","warning":["shellfish/fish","shellfish/fish","shellfish/fish","shellfish/fish","garlic"]},{"name":"Paella Vegetariano","desc":"Saffron rice, mushrooms, peas, asparagus, cauliflower, roasted peppers, garlic aioli","price":"$24.00","warning":["garlic"]},{"name":"Apple Tart","price":"$9.00","warning":["apple"]},{"name":"Tres Leches","price":"$10.00","warning":[]},{"name":"Churros","price":"$10.00","warning":[]},{"name":"Flan","price":"$10.00","warning":[]},{"name":"Maduros","price":"$7.00","warning":[]},{"name":"Tostones","price":"$7.00","warning":[]},{"name":"Arroz Blanco y Frijol Negros","price":"$8.00","warning":[]},{"name":"Yuca Frita","price":"$7.00","warning":[]},{"name":"Arroz Frito Cubano","price":"$7.00","warning":[]},{"name":"French Fries","price":"$7.00","warning":[]},{"name":"ARROZ BLANCO","price":"$5.00","warning":[]},{"name":"MORO","price":"$7.00","warning":[]},{"name":"FRIJOLES NEGROS -","price":"$5.00","warning":[]},{"name":"GARLIC SPINACH","price":"$8.00","warning":["spinach","garlic"]},{"name":"GARLIC BABY KALE","price":"$8.00","warning":["kale","garlic"]}]